{
  "diagnostic.displayByAle": true,
  "languageserver": {
    "terraform": {
      "args": ["serve"],
      "command": "terraform-ls",
      "filetypes": ["terraform"],
      "rootPatterns": [".git/"]
    },
    "puppet": {
      "args": ["--stdio"],
      "command": "puppet-languageserver",
      "filetypes": ["puppet"],
      "rootPatterns": [".git/"]
    }
  },
  "powershell.codeFormatting.autoCorrectAliases": true,
  "powershell.codeFormatting.trimWhitespaceAroundPipe": true,
  "powershell.codeFormatting.useConstantStrings": true,
  "powershell.codeFormatting.useCorrectCasing": true,
  "powershell.codeFormatting.whitespaceBetweenParameters": true,
  "powershell.integratedConsole.showOnStartup": false
}
